inquiring_machine/__init__.py
inquiring_machine/githf.py
inquiring_machine/machina.yaml
inquiring_machine-0.0.2.dist-info/LICENSE
inquiring_machine-0.0.2.dist-info/METADATA
inquiring_machine-0.0.2.dist-info/WHEEL
inquiring_machine-0.0.2.dist-info/top_level.txt
inquiring_machine-0.0.2.dist-info/RECORD
